LICENSE
MANIFEST.in
Makefile
README.md
requirements.txt
requirements_dev.txt
setup.py
chequeconvert/__init__.py
chequeconvert/base.py
chequeconvert/main.py
chequeconvert.egg-info/PKG-INFO
chequeconvert.egg-info/SOURCES.txt
chequeconvert.egg-info/dependency_links.txt
chequeconvert.egg-info/entry_points.txt
chequeconvert.egg-info/pbr.json
chequeconvert.egg-info/top_level.txt