Metadata-Version: 1.1
Name: chequeconvert
Version: 0.0.1
Summary: Convert amount to word for cheque writing
Home-page: https://github.com/pirsquare/chequeconvert
Author: Ryan Liao
Author-email: pirsquare.ryan@gmail.com
License: MIT
Platform: UNKNOWN
Classifier: Development Status :: 4 - Beta
Classifier: Environment :: Web Environment
Classifier: Intended Audience :: Developers
Classifier: Operating System :: OS Independent
Classifier: Programming Language :: Python
